pythonMuse/Muse.py
pythonMuse/MuseBLE.py
pythonMuse/MuseFinder.py
pythonMuse/__init__.py
pythonMuse/biQuadFilters.py
pythonMuse/butterFilters.py
pythonMuse/constants.py
pythonMuse/helper.py
pythonMuse-1.0.0.dist-info/LICENSE
pythonMuse-1.0.0.dist-info/METADATA
pythonMuse-1.0.0.dist-info/WHEEL
pythonMuse-1.0.0.dist-info/top_level.txt
pythonMuse-1.0.0.dist-info/RECORD
